thrads/__init__.py
thrads/client.py
thrads/exceptions.py
thrads/models/__init__.py
thrads/models/ad.py
thrads_sdk-0.1.3.dist-info/METADATA
thrads_sdk-0.1.3.dist-info/WHEEL
thrads_sdk-0.1.3.dist-info/top_level.txt
thrads_sdk-0.1.3.dist-info/RECORD
