Metadata-Version: 2.2
Name: thrads_sdk
Version: 0.1.3
Summary: Python SDK for the Thrads Ad Platform API
Home-page: https://github.com/thrads/thrads-sdk
Author: Thrads Team
Author-email: contact@thrads.ai
License: MIT
Classifier: Programming Language :: Python :: 3
Classifier: License :: OSI Approved :: MIT License
Classifier: Operating System :: OS Independent
Requires-Python: >=3.6
Requires-Dist: requests>=2.25.0
Requires-Dist: Pillow>=8.0.0
Requires-Dist: aiohttp>=3.8.0
Requires-Dist: certifi>=2023.5.7
Dynamic: author
Dynamic: author-email
Dynamic: classifier
Dynamic: description
Dynamic: description-content-type
Dynamic: home-page
Dynamic: license
Dynamic: requires-dist
Dynamic: requires-python
Dynamic: summary
